bfpy/__init__.py
bfpy/bfpy.py
bfpy/icon.jpg
bfpy/ir.py
bfpy/jit.py
bfpy/op.py
bfpy/op_gen.py
bfpy/optimize_gen.py
bfpy/vm.py
bfpy-1.0.4.dist-info/METADATA
bfpy-1.0.4.dist-info/WHEEL
bfpy-1.0.4.dist-info/entry_points.txt
bfpy-1.0.4.dist-info/licenses/LICENSE
bfpy-1.0.4.dist-info/RECORD
