Metadata-Version: 2.1
Name: bfpy
Version: 1.0.4
Summary: A Brainfuck Jit Interpreter, with a simple frontend written in pygame
Author-email: UshioA <shiosshio@outlook.com>
License:                    GNU LESSER GENERAL PUBLIC LICENSE
License-File: LICENSE
Keywords: brainfuck,jit
Classifier: License :: OSI Approved :: GNU Lesser General Public License v3 (LGPLv3)
Classifier: Operating System :: OS Independent
Classifier: Programming Language :: Python :: 3
Requires-Python: >=3.6
Requires-Dist: peachpy
Requires-Dist: pygame-ce
